{
    "AX": {
        "error": 0.011114095224878957, 
        "filter_outliers_dict": {
            "filter_outliers": true, 
            "iterations": 1, 
            "std_devs": 2
        }, 
        "fit": "average", 
        "value": -0.11632208803429638
    }, 
    "H1": {
        "error": 0.010858988259987053, 
        "filter_outliers_dict": {
            "filter_outliers": true, 
            "iterations": 1, 
            "std_devs": 2
        }, 
        "fit": "average", 
        "value": -0.13698746305237086
    }, 
    "H2": {
        "error": 0.009523755153532253, 
        "filter_outliers_dict": {
            "filter_outliers": true, 
            "iterations": 1, 
            "std_devs": 2
        }, 
        "fit": "average", 
        "value": -0.1349386173091163
    }, 
    "L1": {
        "error": 0.009901901899626843, 
        "filter_outliers_dict": {
            "filter_outliers": true, 
            "iterations": 1, 
            "std_devs": 2
        }, 
        "fit": "average", 
        "value": -0.2078933937350435
    }, 
    "L2(CDD)": {
        "error": 0.0, 
        "filter_outliers_dict": {
            "filter_outliers": true, 
            "iterations": 1, 
            "std_devs": 2
        }, 
        "fit": "average", 
        "value": 0.0
    }
}