{
    "AX": {
        "error": 0.0062175094067786875, 
        "filter_outliers_dict": {
            "filter_outliers": true, 
            "iterations": 1, 
            "std_devs": 2
        }, 
        "fit": "average", 
        "value": -0.04632399519864191
    }, 
    "CDD": {
        "error": 1.0417510988051821e-05, 
        "filter_outliers_dict": {
            "filter_outliers": true, 
            "iterations": 1, 
            "std_devs": 10
        }, 
        "fit": "average", 
        "value": 5.1637033792191234e-05
    }, 
    "H1": {
        "error": 0.005301946573194959, 
        "filter_outliers_dict": {
            "filter_outliers": true, 
            "iterations": 1, 
            "std_devs": 2
        }, 
        "fit": "average", 
        "value": -0.029435784872125087
    }, 
    "H2": {
        "error": 0.007062804926406849, 
        "filter_outliers_dict": {
            "filter_outliers": true, 
            "iterations": 1, 
            "std_devs": 2
        }, 
        "fit": "average", 
        "value": -0.19237796959408013
    }, 
    "L1": {
        "error": 0.002674798326524975, 
        "filter_outliers_dict": {
            "filter_outliers": true, 
            "iterations": 1, 
            "std_devs": 2
        }, 
        "fit": "average", 
        "value": -0.019518443854049775
    }, 
    "L2": {
        "error": 0.0057590045932220234, 
        "filter_outliers_dict": {
            "filter_outliers": true, 
            "iterations": 1, 
            "std_devs": 2
        }, 
        "fit": "average", 
        "value": -0.0228198905508919
    }
}