{
    "AX": {
        "error": 0.004866919007343466, 
        "filter_outliers_dict": {
            "filter_outliers": true, 
            "iterations": 1, 
            "std_devs": 2
        }, 
        "fit": "average", 
        "value": -0.05121986841851618
    }, 
    "CDD": {
        "error": 3.933309485855831e-06, 
        "filter_outliers_dict": {
            "filter_outliers": true, 
            "iterations": 1, 
            "std_devs": 10
        }, 
        "fit": "average", 
        "value": 1.3630591227689607e-05
    }, 
    "H1": {
        "error": 0.0032458909320344747, 
        "filter_outliers_dict": {
            "filter_outliers": true, 
            "iterations": 1, 
            "std_devs": 2
        }, 
        "fit": "average", 
        "value": 0.07636634692522429
    }, 
    "H2": {
        "error": 0.0029346277046166957, 
        "filter_outliers_dict": {
            "filter_outliers": true, 
            "iterations": 1, 
            "std_devs": 2
        }, 
        "fit": "average", 
        "value": -0.08439326382945192
    }, 
    "L1": {
        "error": 0.0018337893448681886, 
        "filter_outliers_dict": {
            "filter_outliers": true, 
            "iterations": 1, 
            "std_devs": 2
        }, 
        "fit": "average", 
        "value": -0.03734345991329753
    }, 
    "L2": {
        "error": 0.004452389258075423, 
        "filter_outliers_dict": {
            "filter_outliers": true, 
            "iterations": 1, 
            "std_devs": 2
        }, 
        "fit": "average", 
        "value": -0.021859276116197455
    }
}