{
    "AX": {
        "error": 0.006815646129470858, 
        "filter_outliers_dict": {
            "filter_outliers": true, 
            "iterations": 1, 
            "std_devs": 2
        }, 
        "fit": "average", 
        "value": -0.08335945643248469
    }, 
    "CDD": {
        "error": 2.0354784061088745e-05, 
        "filter_outliers_dict": {
            "filter_outliers": true, 
            "iterations": 1, 
            "std_devs": 10
        }, 
        "fit": "average", 
        "value": 0.0001910439464576478
    }, 
    "H1": {
        "error": 0.004603032992233691, 
        "filter_outliers_dict": {
            "filter_outliers": true, 
            "iterations": 1, 
            "std_devs": 2
        }, 
        "fit": "average", 
        "value": -0.014796059826706379
    }, 
    "H2": {
        "error": 0.007434058031091969, 
        "filter_outliers_dict": {
            "filter_outliers": true, 
            "iterations": 1, 
            "std_devs": 2
        }, 
        "fit": "average", 
        "value": -0.20180624925189233
    }, 
    "L1": {
        "error": 0.0025541917609023233, 
        "filter_outliers_dict": {
            "filter_outliers": true, 
            "iterations": 1, 
            "std_devs": 2
        }, 
        "fit": "average", 
        "value": -0.03903554350730533
    }, 
    "L2": {
        "error": 0.006207301735501774, 
        "filter_outliers_dict": {
            "filter_outliers": true, 
            "iterations": 1, 
            "std_devs": 2
        }, 
        "fit": "average", 
        "value": -0.01664168466176919
    }
}