{
    "AX": {
        "error": 0.005939357646518702, 
        "filter_outliers_dict": {
            "filter_outliers": true, 
            "iterations": 1, 
            "std_devs": 2
        }, 
        "fit": "average", 
        "value": -0.08603682428842813
    }, 
    "CDD": {
        "error": 1.3333720377235954e-05, 
        "filter_outliers_dict": {
            "filter_outliers": true, 
            "iterations": 1, 
            "std_devs": 10
        }, 
        "fit": "average", 
        "value": 8.931924705224343e-05
    }, 
    "H1": {
        "error": 0.0049183521721672075, 
        "filter_outliers_dict": {
            "filter_outliers": true, 
            "iterations": 1, 
            "std_devs": 2
        }, 
        "fit": "average", 
        "value": -0.01912279282381655
    }, 
    "H2": {
        "error": 0.009413218350858564, 
        "filter_outliers_dict": {
            "filter_outliers": true, 
            "iterations": 1, 
            "std_devs": 2
        }, 
        "fit": "average", 
        "value": -0.20424614196615654
    }, 
    "L1": {
        "error": 0.002271951391607859, 
        "filter_outliers_dict": {
            "filter_outliers": true, 
            "iterations": 1, 
            "std_devs": 2
        }, 
        "fit": "average", 
        "value": -0.027287841837594574
    }, 
    "L2": {
        "error": 0.005677179027706662, 
        "filter_outliers_dict": {
            "filter_outliers": true, 
            "iterations": 1, 
            "std_devs": 2
        }, 
        "fit": "average", 
        "value": -0.018299821155390396
    }
}