{
    "AX": {
        "error": 0.006679959472970741, 
        "filter_outliers_dict": {
            "filter_outliers": true, 
            "iterations": 1, 
            "std_devs": 2
        }, 
        "fit": "average", 
        "value": -0.08031366381478389
    }, 
    "CDD": {
        "error": 8.291999244378267e-06, 
        "filter_outliers_dict": {
            "filter_outliers": true, 
            "iterations": 1, 
            "std_devs": 10
        }, 
        "fit": "average", 
        "value": 2.7291992100956482e-05
    }, 
    "H1": {
        "error": 0.016077176963791323, 
        "filter_outliers_dict": {
            "filter_outliers": true, 
            "iterations": 1, 
            "std_devs": 2
        }, 
        "fit": "average", 
        "value": -0.7038994645306388
    }, 
    "H2": {
        "error": 0.00760696635843301, 
        "filter_outliers_dict": {
            "filter_outliers": true, 
            "iterations": 1, 
            "std_devs": 2
        }, 
        "fit": "average", 
        "value": -0.19627962642326255
    }, 
    "L1": {
        "error": 0.003045926883261156, 
        "filter_outliers_dict": {
            "filter_outliers": true, 
            "iterations": 1, 
            "std_devs": 2
        }, 
        "fit": "average", 
        "value": -0.018833049589920454
    }, 
    "L2": {
        "error": 0.006840590517183995, 
        "filter_outliers_dict": {
            "filter_outliers": true, 
            "iterations": 1, 
            "std_devs": 2
        }, 
        "fit": "average", 
        "value": -0.026348284230183257
    }
}