{
    "AX": {
        "error": 0.00555397659256454, 
        "filter_outliers_dict": {
            "filter_outliers": true, 
            "iterations": 1, 
            "std_devs": 2
        }, 
        "fit": "average", 
        "value": -0.04820203138472737
    }, 
    "CDD": {
        "error": 4.428346643751325e-05, 
        "filter_outliers_dict": {
            "filter_outliers": true, 
            "iterations": 1, 
            "std_devs": 10
        }, 
        "fit": "average", 
        "value": 0.0008065213300762719
    }, 
    "H1": {
        "error": 0.011323499869350951, 
        "filter_outliers_dict": {
            "filter_outliers": true, 
            "iterations": 1, 
            "std_devs": 2
        }, 
        "fit": "average", 
        "value": 0.06759548051918209
    }, 
    "H2": {
        "error": 0.008497671151483364, 
        "filter_outliers_dict": {
            "filter_outliers": true, 
            "iterations": 1, 
            "std_devs": 2
        }, 
        "fit": "average", 
        "value": -0.2078810530722655
    }, 
    "L1": {
        "error": 0.0023807199517790747, 
        "filter_outliers_dict": {
            "filter_outliers": true, 
            "iterations": 1, 
            "std_devs": 2
        }, 
        "fit": "average", 
        "value": -0.02032843523229754
    }, 
    "L2": {
        "error": 0.005947149317185907, 
        "filter_outliers_dict": {
            "filter_outliers": true, 
            "iterations": 1, 
            "std_devs": 2
        }, 
        "fit": "average", 
        "value": -0.006419545040676317
    }
}