{
    "AX": {
        "error": 0.005673424877594429, 
        "filter_outliers_dict": {
            "filter_outliers": true, 
            "iterations": 1, 
            "std_devs": 2
        }, 
        "fit": "average", 
        "value": -0.056939824667759896
    }, 
    "CDD": {
        "error": 1.1735878977420454e-05, 
        "filter_outliers_dict": {
            "filter_outliers": true, 
            "iterations": 1, 
            "std_devs": 10
        }, 
        "fit": "average", 
        "value": 5.901375298576126e-05
    }, 
    "H1": {
        "error": 0.004435386547272552, 
        "filter_outliers_dict": {
            "filter_outliers": true, 
            "iterations": 1, 
            "std_devs": 2
        }, 
        "fit": "average", 
        "value": -0.034945495470138706
    }, 
    "H2": {
        "error": 0.005499185024125425, 
        "filter_outliers_dict": {
            "filter_outliers": true, 
            "iterations": 1, 
            "std_devs": 2
        }, 
        "fit": "average", 
        "value": -0.1896555948579521
    }, 
    "L1": {
        "error": 0.0027862324394111273, 
        "filter_outliers_dict": {
            "filter_outliers": true, 
            "iterations": 1, 
            "std_devs": 2
        }, 
        "fit": "average", 
        "value": -0.01568472698928952
    }, 
    "L2": {
        "error": 0.006896258792790693, 
        "filter_outliers_dict": {
            "filter_outliers": true, 
            "iterations": 1, 
            "std_devs": 2
        }, 
        "fit": "average", 
        "value": -0.01822376550431019
    }
}