{
    "AX": {
        "error": 0.00749363852977962, 
        "filter_outliers_dict": {
            "filter_outliers": true, 
            "iterations": 1, 
            "std_devs": 2
        }, 
        "fit": "average", 
        "value": -0.07255468989779225
    }, 
    "CDD": {
        "error": 1.807415847609774e-05, 
        "filter_outliers_dict": {
            "filter_outliers": true, 
            "iterations": 1, 
            "std_devs": 10
        }, 
        "fit": "average", 
        "value": 0.00011661123976839943
    }, 
    "H1": {
        "error": 0.01751231432815746, 
        "filter_outliers_dict": {
            "filter_outliers": true, 
            "iterations": 1, 
            "std_devs": 2
        }, 
        "fit": "average", 
        "value": -0.07122305779651338
    }, 
    "H2": {
        "error": 0.008214538180678433, 
        "filter_outliers_dict": {
            "filter_outliers": true, 
            "iterations": 1, 
            "std_devs": 2
        }, 
        "fit": "average", 
        "value": -0.20536730889812982
    }, 
    "L1": {
        "error": 0.0028780451093016017, 
        "filter_outliers_dict": {
            "filter_outliers": true, 
            "iterations": 1, 
            "std_devs": 2
        }, 
        "fit": "average", 
        "value": -0.022044531629715418
    }, 
    "L2": {
        "error": 0.005929736329569795, 
        "filter_outliers_dict": {
            "filter_outliers": true, 
            "iterations": 1, 
            "std_devs": 2
        }, 
        "fit": "average", 
        "value": -0.01026548504095218
    }
}