{
    "Ar36": {
        "error": 0.0003006405778097864, 
        "fit": "previous", 
        "references": [
            {
                "exclude": false, 
                "record_id": "bc-02-F-211"
            }
        ], 
        "value": 0.0026321445024110697
    }, 
    "Ar37": {
        "error": 0.01262305464927275, 
        "fit": "previous", 
        "references": [
            {
                "exclude": false, 
                "record_id": "bc-02-F-211"
            }
        ], 
        "value": 0.028549263395925284
    }, 
    "Ar38": {
        "error": 0.012334585723162095, 
        "fit": "previous", 
        "references": [
            {
                "exclude": false, 
                "record_id": "bc-02-F-211"
            }
        ], 
        "value": -0.025991772000287836
    }, 
    "Ar39": {
        "error": 0.023007713354926903, 
        "fit": "previous", 
        "references": [
            {
                "exclude": false, 
                "record_id": "bc-02-F-211"
            }
        ], 
        "value": -0.04525094757471072
    }, 
    "Ar40": {
        "error": 0.020306293050790923, 
        "fit": "previous", 
        "references": [
            {
                "exclude": false, 
                "record_id": "bc-02-F-211"
            }
        ], 
        "value": 0.6145008887670544
    }
}