{
    "Ar36": {
        "error": 0.0003328932376357173, 
        "filter_outliers_dict": {
            "filter_outliers": true, 
            "iterations": 1, 
            "std_devs": 2
        }, 
        "fit": "Linear", 
        "value": 0.014647400533974776
    }, 
    "Ar37": {
        "error": 0.010392392540395215, 
        "filter_outliers_dict": {
            "filter_outliers": true, 
            "iterations": 1, 
            "std_devs": 2
        }, 
        "fit": "linear", 
        "value": 0.005412608837497042
    }, 
    "Ar38": {
        "error": 0.004511450463858336, 
        "filter_outliers_dict": {
            "filter_outliers": true, 
            "iterations": 1, 
            "std_devs": 2
        }, 
        "fit": "linear", 
        "value": 0.15293761646926296
    }, 
    "Ar39": {
        "error": 0.012400512536209057, 
        "filter_outliers_dict": {
            "filter_outliers": true, 
            "iterations": 1, 
            "std_devs": 2
        }, 
        "fit": "Linear", 
        "value": 11.873099730814005
    }, 
    "Ar40": {
        "error": 0.09799496751229561, 
        "filter_outliers_dict": {
            "filter_outliers": true, 
            "iterations": 1, 
            "std_devs": 2
        }, 
        "fit": "Linear", 
        "value": 2121.526897722034
    }, 
    "Ar41": {
        "error": 0.005726534564709492, 
        "filter_outliers_dict": {
            "filter_outliers": true, 
            "iterations": 1, 
            "std_devs": 2
        }, 
        "fit": "Average", 
        "value": -0.058243238259882014
    }
}