{
    "Ar36": {
        "error": 0.00026238628834118755, 
        "filter_outliers_dict": {
            "filter_outliers": true, 
            "iterations": 2, 
            "std_devs": 2
        }, 
        "fit": "Parabolic", 
        "value": 0.015751010189661862
    }, 
    "Ar37": {
        "error": 0.011688761100231343, 
        "filter_outliers_dict": {
            "filter_outliers": true, 
            "iterations": 2, 
            "std_devs": 2
        }, 
        "fit": "linear", 
        "value": -0.1877902019940461
    }, 
    "Ar38": {
        "error": 0.013788790773090122, 
        "filter_outliers_dict": {
            "filter_outliers": true, 
            "iterations": 2, 
            "std_devs": 2
        }, 
        "fit": "linear", 
        "value": -0.0681789020976922
    }, 
    "Ar39": {
        "error": 0.02357708673327507, 
        "filter_outliers_dict": {
            "filter_outliers": true, 
            "iterations": 2, 
            "std_devs": 2
        }, 
        "fit": "Parabolic", 
        "value": 0.3845507158712488
    }, 
    "Ar40": {
        "error": 0.020009080477162485, 
        "filter_outliers_dict": {
            "filter_outliers": true, 
            "iterations": 2, 
            "std_devs": 2
        }, 
        "fit": "Parabolic", 
        "value": 23.597194898122716
    }
}