{
    "Ar36": {
        "error": 0.0009025091613601876, 
        "filter_outliers_dict": {
            "filter_outliers": true, 
            "iterations": 2, 
            "std_devs": 2
        }, 
        "fit": "Parabolic", 
        "value": 0.13812467310889054
    }, 
    "Ar37": {
        "error": 0.010746151832782965, 
        "filter_outliers_dict": {
            "filter_outliers": true, 
            "iterations": 2, 
            "std_devs": 2
        }, 
        "fit": "linear", 
        "value": -0.023861821525808735
    }, 
    "Ar38": {
        "error": 0.013639993909737531, 
        "filter_outliers_dict": {
            "filter_outliers": true, 
            "iterations": 2, 
            "std_devs": 2
        }, 
        "fit": "linear", 
        "value": 0.35937751056561884
    }, 
    "Ar39": {
        "error": 0.024708362899015093, 
        "filter_outliers_dict": {
            "filter_outliers": true, 
            "iterations": 2, 
            "std_devs": 2
        }, 
        "fit": "Parabolic", 
        "value": 30.643123001594553
    }, 
    "Ar40": {
        "error": 0.3803394992311401, 
        "filter_outliers_dict": {
            "filter_outliers": true, 
            "iterations": 2, 
            "std_devs": 2
        }, 
        "fit": "Parabolic", 
        "value": 4666.360198118002
    }
}