{
    "Ar36": {
        "error": 0.00026837950316724535, 
        "filter_outliers_dict": {
            "filter_outliers": true, 
            "iterations": 1, 
            "std_devs": 2
        }, 
        "fit": "Linear", 
        "value": 0.009005580657617307
    }, 
    "Ar37": {
        "error": 0.01075584153385163, 
        "filter_outliers_dict": {
            "filter_outliers": true, 
            "iterations": 1, 
            "std_devs": 2
        }, 
        "fit": "linear", 
        "value": 0.03162914989749492
    }, 
    "Ar38": {
        "error": 0.004206761999987877, 
        "filter_outliers_dict": {
            "filter_outliers": true, 
            "iterations": 1, 
            "std_devs": 2
        }, 
        "fit": "linear", 
        "value": -0.00775586295199917
    }, 
    "Ar39": {
        "error": 0.012351458297310249, 
        "filter_outliers_dict": {
            "filter_outliers": true, 
            "iterations": 1, 
            "std_devs": 2
        }, 
        "fit": "Linear", 
        "value": 0.23169232465531325
    }, 
    "Ar40": {
        "error": 0.010232557605334846, 
        "filter_outliers_dict": {
            "filter_outliers": true, 
            "iterations": 1, 
            "std_devs": 2
        }, 
        "fit": "Linear", 
        "value": 17.656578504335037
    }, 
    "PM41": {
        "error": 0.08013806290393467, 
        "filter_outliers_dict": {
            "filter_outliers": false, 
            "iterations": 1, 
            "std_devs": 2
        }, 
        "fit": "linear", 
        "value": -0.14753806575638734
    }
}