{
    "Ar36": {
        "error": 0.00020824641923982372, 
        "filter_outliers_dict": {
            "filter_outliers": true, 
            "iterations": 1, 
            "std_devs": 2
        }, 
        "fit": "Linear", 
        "value": 0.004533843366771188
    }, 
    "Ar37": {
        "error": 0.011094474565713969, 
        "filter_outliers_dict": {
            "filter_outliers": true, 
            "iterations": 1, 
            "std_devs": 2
        }, 
        "fit": "linear", 
        "value": 0.03465295582565567
    }, 
    "Ar38": {
        "error": 0.004478454121002543, 
        "filter_outliers_dict": {
            "filter_outliers": true, 
            "iterations": 1, 
            "std_devs": 2
        }, 
        "fit": "linear", 
        "value": -0.005469614891004113
    }, 
    "Ar39": {
        "error": 0.012679649271964159, 
        "filter_outliers_dict": {
            "filter_outliers": true, 
            "iterations": 1, 
            "std_devs": 2
        }, 
        "fit": "Linear", 
        "value": -0.06408173912824892
    }, 
    "Ar40": {
        "error": 0.007986491775979413, 
        "filter_outliers_dict": {
            "filter_outliers": true, 
            "iterations": 1, 
            "std_devs": 2
        }, 
        "fit": "Linear", 
        "value": 0.6475705256557273
    }, 
    "PM41": {
        "error": 0.05995993235198619, 
        "filter_outliers_dict": {
            "filter_outliers": false, 
            "iterations": 1, 
            "std_devs": 2
        }, 
        "fit": "linear", 
        "value": -0.1864177504876073
    }
}