{
    "Ar36": {
        "error": 0.0014258840354996424, 
        "filter_outliers_dict": {
            "filter_outliers": true, 
            "iterations": 1, 
            "std_devs": 2
        }, 
        "fit": "Linear", 
        "value": 0.30885560150127206
    }, 
    "Ar37": {
        "error": 0.010963872818031696, 
        "filter_outliers_dict": {
            "filter_outliers": true, 
            "iterations": 1, 
            "std_devs": 2
        }, 
        "fit": "linear", 
        "value": 0.027334234597993366
    }, 
    "Ar38": {
        "error": 0.004243941271674434, 
        "filter_outliers_dict": {
            "filter_outliers": true, 
            "iterations": 1, 
            "std_devs": 2
        }, 
        "fit": "linear", 
        "value": 0.10181787472239114
    }, 
    "Ar39": {
        "error": 0.012058515777867639, 
        "filter_outliers_dict": {
            "filter_outliers": true, 
            "iterations": 1, 
            "std_devs": 2
        }, 
        "fit": "Linear", 
        "value": 0.6196537609724437
    }, 
    "Ar40": {
        "error": 0.018947065045804533, 
        "filter_outliers_dict": {
            "filter_outliers": true, 
            "iterations": 1, 
            "std_devs": 2
        }, 
        "fit": "Linear", 
        "value": 179.3979935127733
    }, 
    "Ar41": {
        "error": 0.006102745506535668, 
        "filter_outliers_dict": {
            "filter_outliers": true, 
            "iterations": 1, 
            "std_devs": 2
        }, 
        "fit": "Average", 
        "value": -0.16310666217173925
    }
}