{
    "Ar36": {
        "error": 0.00012713679620258823, 
        "filter_outliers_dict": {
            "filter_outliers": true, 
            "iterations": 1, 
            "std_devs": 2
        }, 
        "fit": "Linear", 
        "value": 0.008554210725583785
    }, 
    "Ar37": {
        "error": 0.00505541835615406, 
        "filter_outliers_dict": {
            "filter_outliers": true, 
            "iterations": 1, 
            "std_devs": 2
        }, 
        "fit": "linear", 
        "value": 0.02740835260802413
    }, 
    "Ar38": {
        "error": 0.002505683051958165, 
        "filter_outliers_dict": {
            "filter_outliers": true, 
            "iterations": 1, 
            "std_devs": 2
        }, 
        "fit": "linear", 
        "value": -0.028147762678377427
    }, 
    "Ar39": {
        "error": 0.005591407390699579, 
        "filter_outliers_dict": {
            "filter_outliers": true, 
            "iterations": 1, 
            "std_devs": 2
        }, 
        "fit": "Linear", 
        "value": 0.08795201013572533
    }, 
    "Ar40": {
        "error": 0.008196071725126132, 
        "filter_outliers_dict": {
            "filter_outliers": true, 
            "iterations": 1, 
            "std_devs": 2
        }, 
        "fit": "Linear", 
        "value": 11.250134365808279
    }, 
    "Ar41": {
        "error": 0.0016539820864277172, 
        "filter_outliers_dict": {
            "filter_outliers": true, 
            "iterations": 1, 
            "std_devs": 2
        }, 
        "fit": "Average", 
        "value": -0.06947310444744847
    }
}