{
    "Ar36": {
        "error": 0.0004158398040927843, 
        "filter_outliers_dict": {
            "filter_outliers": true, 
            "iterations": 1, 
            "std_devs": 2
        }, 
        "fit": "Linear", 
        "value": 0.011227694464963155
    }, 
    "Ar37": {
        "error": 0.016502288348396704, 
        "filter_outliers_dict": {
            "filter_outliers": true, 
            "iterations": 1, 
            "std_devs": 2
        }, 
        "fit": "linear", 
        "value": 0.05151032654319152
    }, 
    "Ar38": {
        "error": 0.0073073206552955175, 
        "filter_outliers_dict": {
            "filter_outliers": true, 
            "iterations": 1, 
            "std_devs": 2
        }, 
        "fit": "linear", 
        "value": -0.0027107324339693145
    }, 
    "Ar39": {
        "error": 0.018366895125716202, 
        "filter_outliers_dict": {
            "filter_outliers": true, 
            "iterations": 1, 
            "std_devs": 2
        }, 
        "fit": "Linear", 
        "value": 1.59390303473537
    }, 
    "Ar40": {
        "error": 0.06214000504360791, 
        "filter_outliers_dict": {
            "filter_outliers": true, 
            "iterations": 1, 
            "std_devs": 2
        }, 
        "fit": "Linear", 
        "value": 147.67289097450802
    }, 
    "PM41": {
        "error": 0.06664938050609273, 
        "filter_outliers_dict": {
            "filter_outliers": false, 
            "iterations": 1, 
            "std_devs": 2
        }, 
        "fit": "linear", 
        "value": -0.11059887770315377
    }
}