{
    "Ar36": {
        "error": 0.0003264350585846415, 
        "filter_outliers_dict": {
            "filter_outliers": true, 
            "iterations": 2, 
            "std_devs": 2
        }, 
        "fit": "Parabolic", 
        "value": 0.016392357686255975
    }, 
    "Ar37": {
        "error": 0.012492521477279186, 
        "filter_outliers_dict": {
            "filter_outliers": true, 
            "iterations": 2, 
            "std_devs": 2
        }, 
        "fit": "linear", 
        "value": -0.9495207117159744
    }, 
    "Ar38": {
        "error": 0.01303090352092769, 
        "filter_outliers_dict": {
            "filter_outliers": true, 
            "iterations": 2, 
            "std_devs": 2
        }, 
        "fit": "linear", 
        "value": -0.09957292372778603
    }, 
    "Ar39": {
        "error": 0.024247447515082385, 
        "filter_outliers_dict": {
            "filter_outliers": true, 
            "iterations": 2, 
            "std_devs": 2
        }, 
        "fit": "Parabolic", 
        "value": 1.5531872783536718
    }, 
    "Ar40": {
        "error": 0.03492934905397375, 
        "filter_outliers_dict": {
            "filter_outliers": true, 
            "iterations": 2, 
            "std_devs": 2
        }, 
        "fit": "Parabolic", 
        "value": 147.13441164627127
    }
}