{
    "Ar36": {
        "error": 0.00026743205232808854, 
        "filter_outliers_dict": {
            "filter_outliers": true, 
            "iterations": 1, 
            "std_devs": 2
        }, 
        "fit": "Linear", 
        "value": 0.009811225731285388
    }, 
    "Ar37": {
        "error": 0.010931301000027442, 
        "filter_outliers_dict": {
            "filter_outliers": true, 
            "iterations": 1, 
            "std_devs": 2
        }, 
        "fit": "linear", 
        "value": 0.0023426864875927766
    }, 
    "Ar38": {
        "error": 0.004955006108437038, 
        "filter_outliers_dict": {
            "filter_outliers": true, 
            "iterations": 1, 
            "std_devs": 2
        }, 
        "fit": "linear", 
        "value": -0.0036248028325743626
    }, 
    "Ar39": {
        "error": 0.011684267261060682, 
        "filter_outliers_dict": {
            "filter_outliers": true, 
            "iterations": 1, 
            "std_devs": 2
        }, 
        "fit": "Linear", 
        "value": 0.029568501360264232
    }, 
    "Ar40": {
        "error": 0.01108650880430715, 
        "filter_outliers_dict": {
            "filter_outliers": true, 
            "iterations": 1, 
            "std_devs": 2
        }, 
        "fit": "Linear", 
        "value": 5.390641195817858
    }, 
    "Ar41": {
        "error": 0.005438207755884925, 
        "filter_outliers_dict": {
            "filter_outliers": true, 
            "iterations": 1, 
            "std_devs": 2
        }, 
        "fit": "Average", 
        "value": -0.1679851045382085
    }
}