{
    "Ar36": {
        "error": 0.0003207209119394167, 
        "filter_outliers_dict": {
            "filter_outliers": true, 
            "iterations": 1, 
            "std_devs": 2
        }, 
        "fit": "Linear", 
        "value": 0.012028670913983162
    }, 
    "Ar37": {
        "error": 0.00924899844867076, 
        "filter_outliers_dict": {
            "filter_outliers": true, 
            "iterations": 1, 
            "std_devs": 2
        }, 
        "fit": "linear", 
        "value": 0.0399636471350778
    }, 
    "Ar38": {
        "error": 0.00445070620264931, 
        "filter_outliers_dict": {
            "filter_outliers": true, 
            "iterations": 1, 
            "std_devs": 2
        }, 
        "fit": "linear", 
        "value": 0.022319836849605448
    }, 
    "Ar39": {
        "error": 0.01220494638698149, 
        "filter_outliers_dict": {
            "filter_outliers": true, 
            "iterations": 1, 
            "std_devs": 2
        }, 
        "fit": "Linear", 
        "value": 3.4874411955260376
    }, 
    "Ar40": {
        "error": 0.02982227228459921, 
        "filter_outliers_dict": {
            "filter_outliers": true, 
            "iterations": 1, 
            "std_devs": 2
        }, 
        "fit": "Linear", 
        "value": 313.21263774390246
    }, 
    "PM41": {
        "error": 0.060269897020148816, 
        "filter_outliers_dict": {
            "filter_outliers": false, 
            "iterations": 1, 
            "std_devs": 2
        }, 
        "fit": "linear", 
        "value": -0.14504390870498968
    }
}