{
    "Ar36": {
        "error": 0.00030346696757872896, 
        "filter_outliers_dict": {
            "filter_outliers": true, 
            "iterations": 2, 
            "std_devs": 2
        }, 
        "fit": "Parabolic", 
        "value": 0.01763108344818172
    }, 
    "Ar37": {
        "error": 0.010572709418778648, 
        "filter_outliers_dict": {
            "filter_outliers": true, 
            "iterations": 2, 
            "std_devs": 2
        }, 
        "fit": "linear", 
        "value": -0.25347345194683624
    }, 
    "Ar38": {
        "error": 0.012428461979791038, 
        "filter_outliers_dict": {
            "filter_outliers": true, 
            "iterations": 2, 
            "std_devs": 2
        }, 
        "fit": "linear", 
        "value": -0.07264779416720285
    }, 
    "Ar39": {
        "error": 0.02185675408130795, 
        "filter_outliers_dict": {
            "filter_outliers": true, 
            "iterations": 2, 
            "std_devs": 2
        }, 
        "fit": "Parabolic", 
        "value": 1.8199883513579256
    }, 
    "Ar40": {
        "error": 0.026191918632496702, 
        "filter_outliers_dict": {
            "filter_outliers": true, 
            "iterations": 2, 
            "std_devs": 2
        }, 
        "fit": "Parabolic", 
        "value": 139.8664397308765
    }
}