{
    "Ar36": {
        "error": 0.0033252307284199864, 
        "filter_outliers_dict": {
            "filter_outliers": true, 
            "iterations": 2, 
            "std_devs": 2
        }, 
        "fit": "Parabolic", 
        "value": 2.7816584312983905
    }, 
    "Ar37": {
        "error": 0.010776074603463371, 
        "filter_outliers_dict": {
            "filter_outliers": true, 
            "iterations": 2, 
            "std_devs": 2
        }, 
        "fit": "linear", 
        "value": -0.27767012945696296
    }, 
    "Ar38": {
        "error": 0.013690841850033964, 
        "filter_outliers_dict": {
            "filter_outliers": true, 
            "iterations": 2, 
            "std_devs": 2
        }, 
        "fit": "linear", 
        "value": 0.4355240142138658
    }, 
    "Ar39": {
        "error": 0.023098863659183507, 
        "filter_outliers_dict": {
            "filter_outliers": true, 
            "iterations": 2, 
            "std_devs": 2
        }, 
        "fit": "Parabolic", 
        "value": 0.05000662899747894
    }, 
    "Ar40": {
        "error": 0.06020745277012256, 
        "filter_outliers_dict": {
            "filter_outliers": true, 
            "iterations": 2, 
            "std_devs": 2
        }, 
        "fit": "Parabolic", 
        "value": 833.3462038193283
    }
}