{
    "AX": {
        "error": 0.006340262687879003, 
        "filter_outliers_dict": {
            "filter_outliers": true, 
            "iterations": 1, 
            "std_devs": 2
        }, 
        "fit": "average", 
        "value": -0.08304848190570295
    }, 
    "CDD": {
        "error": 1.1717757129886564e-05, 
        "filter_outliers_dict": {
            "filter_outliers": true, 
            "iterations": 1, 
            "std_devs": 10
        }, 
        "fit": "average", 
        "value": 5.458398429655904e-05
    }, 
    "H1": {
        "error": 0.01592864610350798, 
        "filter_outliers_dict": {
            "filter_outliers": true, 
            "iterations": 1, 
            "std_devs": 2
        }, 
        "fit": "average", 
        "value": -0.9729289237805263
    }, 
    "H2": {
        "error": 0.007631582905847801, 
        "filter_outliers_dict": {
            "filter_outliers": true, 
            "iterations": 1, 
            "std_devs": 2
        }, 
        "fit": "average", 
        "value": -0.1859196090365776
    }, 
    "L1": {
        "error": 0.0033098561163098805, 
        "filter_outliers_dict": {
            "filter_outliers": true, 
            "iterations": 1, 
            "std_devs": 2
        }, 
        "fit": "average", 
        "value": -0.027041241942057186
    }, 
    "L2": {
        "error": 0.005504021800498355, 
        "filter_outliers_dict": {
            "filter_outliers": true, 
            "iterations": 1, 
            "std_devs": 2
        }, 
        "fit": "average", 
        "value": -0.021862102283135624
    }
}